README.rst
setup.py
mynumber/__init__.py
mynumber/mynumber.py
mynumber.egg-info/PKG-INFO
mynumber.egg-info/SOURCES.txt
mynumber.egg-info/dependency_links.txt
mynumber.egg-info/not-zip-safe
mynumber.egg-info/top_level.txt