Metadata-Version: 1.1
Name: mynumber
Version: 0.0.4
Summary: 'My Number' validate module
Home-page: https://github.com/subc/mynumber
Author: haminiku
Author-email: haminiku1129@gmail.com
License: MIT License
Keywords: 'My Number',Japan,My Number system,mynumber
Platform: UNKNOWN
Classifier: License :: OSI Approved :: MIT License
Classifier: Programming Language :: Python
Classifier: Programming Language :: Python :: 2.6
Classifier: Programming Language :: Python :: 2.7
Classifier: Programming Language :: Python :: 3
Classifier: Programming Language :: Python :: 3.3
Classifier: Programming Language :: Python :: 3.4
